{"status":{"timestamp":"2021-11-01T00:45:41.809Z","error_code":0,"error_message":null,"elapsed":14,"credit_count":1,"notice":null},"data":{"active_cryptocurrencies":6907,"total_cryptocurrencies":13349,"active_market_pairs":47699,"active_exchanges":425,"total_exchanges":1516,"eth_dominance":19.311735752814,"btc_dominance":43.994603444697,"eth_dominance_yesterday":19.50242097,"btc_dominance_yesterday":44.27193892,"eth_dominance_24h_percentage_change":-0.190685217186,"btc_dominance_24h_percentage_change":-0.277335475303,"defi_volume_24h":18103144211.551987,"defi_volume_24h_reported":18103144211.551987,"defi_market_cap":149325407549.22903,"defi_24h_percentage_change":12.797298952135,"stablecoin_volume_24h":102945106395.3835,"stablecoin_volume_24h_reported":102945106395.3835,"stablecoin_market_cap":130653742689.81282,"stablecoin_24h_percentage_change":0.784139017155,"derivatives_volume_24h":189630230100.91364,"derivatives_volume_24h_reported":189630230100.91364,"derivatives_24h_percentage_change":0.926484701349,"quote":{"USD":{"total_market_cap":2631349266142.2124,"total_volume_24h":136824006483.52,"total_volume_24h_reported":136824006483.52,"altcoin_volume_24h":104855802182.79396,"altcoin_volume_24h_reported":104855802182.79396,"altcoin_market_cap":1473697591258.0027,"defi_volume_24h":18103144211.551987,"defi_volume_24h_reported":18103144211.551987,"defi_24h_percentage_change":12.797298952135,"defi_market_cap":149325407549.22903,"stablecoin_volume_24h":102945106395.3835,"stablecoin_volume_24h_reported":102945106395.3835,"stablecoin_24h_percentage_change":0.784139017155,"stablecoin_market_cap":130653742689.81282,"derivatives_volume_24h":189630230100.91364,"derivatives_volume_24h_reported":189630230100.91364,"derivatives_24h_percentage_change":0.926484701349,"last_updated":"2021-11-01T00:45:10.999Z","total_market_cap_yesterday":2655058401831.2456,"total_volume_24h_yesterday":138193524392.14,"total_market_cap_yesterday_percentage_change":-0.8929798181719946,"total_volume_24h_yesterday_percentage_change":-0.9910145317184771}},"last_updated":"2021-11-01T00:45:10.999Z"}}
{"status":{"timestamp":"2021-11-01T01:58:20.386Z","error_code":0,"error_message":null,"elapsed":13,"credit_count":1,"notice":null},"data":{"active_cryptocurrencies":6914,"total_cryptocurrencies":13355,"active_market_pairs":47711,"active_exchanges":425,"total_exchanges":1517,"eth_dominance":19.303060949052,"btc_dominance":44.020929991878,"eth_dominance_yesterday":19.4996872,"btc_dominance_yesterday":44.38699421,"eth_dominance_24h_percentage_change":-0.196626250948,"btc_dominance_24h_percentage_change":-0.366064218122,"defi_volume_24h":17626296967.09945,"defi_volume_24h_reported":17626296967.09945,"defi_market_cap":149030287385.97665,"defi_24h_percentage_change":6.171636495891,"stablecoin_volume_24h":101016548713.53891,"stablecoin_volume_24h_reported":101016548713.53891,"stablecoin_market_cap":130702638083.11647,"stablecoin_24h_percentage_change":-4.070084129091,"derivatives_volume_24h":185553620194.57278,"derivatives_volume_24h_reported":185553620194.57278,"derivatives_24h_percentage_change":-4.26387502218,"quote":{"USD":{"total_market_cap":2631658827611.095,"total_volume_24h":133239199830.53,"total_volume_24h_reported":133239199830.53,"altcoin_volume_24h":101539741102.45543,"altcoin_volume_24h_reported":101539741102.45543,"altcoin_market_cap":1473178137483.3325,"defi_volume_24h":17626296967.09945,"defi_volume_24h_reported":17626296967.09945,"defi_24h_percentage_change":6.171636495891,"defi_market_cap":149030287385.97665,"stablecoin_volume_24h":101016548713.53891,"stablecoin_volume_24h_reported":101016548713.53891,"stablecoin_24h_percentage_change":-4.070084129091,"stablecoin_market_cap":130702638083.11647,"derivatives_volume_24h":185553620194.57278,"derivatives_volume_24h_reported":185553620194.57278,"derivatives_24h_percentage_change":-4.26387502218,"last_updated":"2021-11-01T01:57:10.999Z","total_market_cap_yesterday":2641606824739.3574,"total_volume_24h_yesterday":143507198640.51,"total_market_cap_yesterday_percentage_change":-0.3765888638345558,"total_volume_24h_yesterday_percentage_change":-7.155040936797647}},"last_updated":"2021-11-01T01:57:10.999Z"}}
{"status":{"timestamp":"2021-11-01T02:33:35.311Z","error_code":0,"error_message":null,"elapsed":14,"credit_count":1,"notice":null},"data":{"active_cryptocurrencies":6915,"total_cryptocurrencies":13357,"active_market_pairs":47712,"active_exchanges":425,"total_exchanges":1517,"eth_dominance":19.268731390197,"btc_dominance":43.997964205448,"eth_dominance_yesterday":19.54837975,"btc_dominance_yesterday":44.26491189,"eth_dominance_24h_percentage_change":-0.279648359803,"btc_dominance_24h_percentage_change":-0.266947684552,"defi_volume_24h":17476165757.943855,"defi_volume_24h_reported":17476165757.943855,"defi_market_cap":146195850817.1723,"defi_24h_percentage_change":4.520568344204,"stablecoin_volume_24h":101422395971.49014,"stablecoin_volume_24h_reported":101422395971.49014,"stablecoin_market_cap":130687093536.17767,"stablecoin_24h_percentage_change":-4.210511800238,"derivatives_volume_24h":188898934394.67566,"derivatives_volume_24h_reported":188898934394.67566,"derivatives_24h_percentage_change":-3.208873546208,"quote":{"USD":{"total_market_cap":2586870752618.7646,"total_volume_24h":133070574693.75,"total_volume_24h_reported":133070574693.75,"altcoin_volume_24h":100999569873.8344,"altcoin_volume_24h_reported":100999569873.8344,"altcoin_market_cap":1448700284840.3694,"defi_volume_24h":17476165757.943855,"defi_volume_24h_reported":17476165757.943855,"defi_24h_percentage_change":4.520568344204,"defi_market_cap":146195850817.1723,"stablecoin_volume_24h":101422395971.49014,"stablecoin_volume_24h_reported":101422395971.49014,"stablecoin_24h_percentage_change":-4.210511800238,"stablecoin_market_cap":130687093536.17767,"derivatives_volume_24h":188898934394.67566,"derivatives_volume_24h_reported":188898934394.67566,"derivatives_24h_percentage_change":-3.208873546208,"last_updated":"2021-11-01T02:33:10.999Z","total_market_cap_yesterday":2653077937418.1855,"total_volume_24h_yesterday":144151562155.31,"total_market_cap_yesterday_percentage_change":-2.4954858606170376,"total_volume_24h_yesterday_percentage_change":-7.687039457554576}},"last_updated":"2021-11-01T02:33:10.999Z"}}
