{"status":{"timestamp":"2025-08-01T00:24:06.147Z","error_code":0,"error_message":null,"elapsed":12,"credit_count":1,"notice":null},"data":{"active_cryptocurrencies":9479,"total_cryptocurrencies":35482,"active_market_pairs":106729,"active_exchanges":834,"total_exchanges":10795,"eth_dominance":11.801559336167,"btc_dominance":60.96192680488,"eth_dominance_yesterday":11.91094864,"btc_dominance_yesterday":60.81115679,"eth_dominance_24h_percentage_change":-0.109389303833,"btc_dominance_24h_percentage_change":0.15077001488,"defi_volume_24h":40647545079.86047,"defi_volume_24h_reported":85111067200.66702,"defi_market_cap":103592376018.10951,"defi_24h_percentage_change":-6.172001600132,"stablecoin_volume_24h":159686941638.61057,"stablecoin_volume_24h_reported":812607345366.5153,"stablecoin_market_cap":248641278300.66144,"stablecoin_24h_percentage_change":-3.198998984886,"derivatives_volume_24h":1522287811065.5146,"derivatives_volume_24h_reported":1522287811065.5146,"derivatives_24h_percentage_change":-11.437075789417,"total_crypto_dex_currencies":18945002,"today_incremental_crypto_number":2,"past_24h_incremental_crypto_number":18990,"past_7d_incremental_crypto_number":159020,"past_30d_incremental_crypto_number":947157,"today_change_percent":0.011144022314,"tracked_yearly_number":{"maxIncrementalNumber":184087,"minIncrementalNumber":2112,"maxIncrementalDate":"2025-04-17T00:00:00.000Z","minIncrementalDate":"2025-07-31T00:00:00.000Z"},"quote":{"USD":{"total_market_cap":3780334061037.4863,"total_volume_24h":165289382253.31,"total_volume_24h_reported":829790127199.94,"altcoin_volume_24h":95661394494.79974,"altcoin_volume_24h_reported":583418864092.0243,"altcoin_market_cap":1475769577767.8574,"defi_volume_24h":40647545079.86047,"defi_volume_24h_reported":85111067200.66702,"defi_24h_percentage_change":-6.172001600132,"defi_market_cap":103592376018.10951,"stablecoin_volume_24h":159686941638.61057,"stablecoin_volume_24h_reported":812607345366.5153,"stablecoin_24h_percentage_change":-3.198998984886,"stablecoin_market_cap":248641278300.66144,"derivatives_volume_24h":1522287811065.5146,"derivatives_volume_24h_reported":1522287811065.5146,"derivatives_24h_percentage_change":-11.437075789417,"total_market_cap_yesterday":3859998411061.607,"total_volume_24h_yesterday":170682637030.87,"total_market_cap_yesterday_percentage_change":-2.063844114438652,"total_volume_24h_yesterday_percentage_change":-3.1598145373067865,"last_updated":"2025-08-01T00:22:59.999Z"}},"last_updated":"2025-08-01T00:22:59.999Z"}}
{"status":{"timestamp":"2025-08-01T01:34:24.101Z","error_code":0,"error_message":null,"elapsed":33,"credit_count":1,"notice":null},"data":{"active_cryptocurrencies":9479,"total_cryptocurrencies":35482,"active_market_pairs":106728,"active_exchanges":834,"total_exchanges":10795,"eth_dominance":11.819911471643,"btc_dominance":60.962314772855,"eth_dominance_yesterday":11.96145195,"btc_dominance_yesterday":60.70179528,"eth_dominance_24h_percentage_change":-0.141540478357,"btc_dominance_24h_percentage_change":0.260519492855,"defi_volume_24h":41387506311.726135,"defi_volume_24h_reported":88352998411.72711,"defi_market_cap":103212360448.39326,"defi_24h_percentage_change":-4.709211182515,"stablecoin_volume_24h":170498817678.24957,"stablecoin_volume_24h_reported":878769536317.4463,"stablecoin_market_cap":248676874071.67017,"stablecoin_24h_percentage_change":1.996128173557,"derivatives_volume_24h":1636846929576.5618,"derivatives_volume_24h_reported":1636846929576.5618,"derivatives_24h_percentage_change":-7.280915154252,"total_crypto_dex_currencies":18945002,"today_incremental_crypto_number":2,"past_24h_incremental_crypto_number":18990,"past_7d_incremental_crypto_number":159020,"past_30d_incremental_crypto_number":947157,"today_change_percent":0.011144022314,"tracked_yearly_number":{"maxIncrementalNumber":184087,"minIncrementalNumber":2112,"maxIncrementalDate":"2025-04-17T00:00:00.000Z","minIncrementalDate":"2025-07-31T00:00:00.000Z"},"quote":{"USD":{"total_market_cap":3757655227067.503,"total_volume_24h":176162852360.31,"total_volume_24h_reported":898579570159.84,"altcoin_volume_24h":101551970254.39542,"altcoin_volume_24h_reported":626593588970.3265,"altcoin_market_cap":1466901619463.971,"defi_volume_24h":41387506311.726135,"defi_volume_24h_reported":88352998411.72711,"defi_24h_percentage_change":-4.709211182515,"defi_market_cap":103212360448.39326,"stablecoin_volume_24h":170498817678.24957,"stablecoin_volume_24h_reported":878769536317.4463,"stablecoin_24h_percentage_change":1.996128173557,"stablecoin_market_cap":248676874071.67017,"derivatives_volume_24h":1636846929576.5618,"derivatives_volume_24h_reported":1636846929576.5618,"derivatives_24h_percentage_change":-7.280915154252,"total_market_cap_yesterday":3876884253682.3555,"total_volume_24h_yesterday":172516974414.89,"total_market_cap_yesterday_percentage_change":-3.075382673640732,"total_volume_24h_yesterday_percentage_change":2.1133444739483593,"last_updated":"2025-08-01T01:32:59.999Z"}},"last_updated":"2025-08-01T01:32:59.999Z"}}
{"status":{"timestamp":"2025-08-01T02:51:40.638Z","error_code":0,"error_message":null,"elapsed":15,"credit_count":1,"notice":null},"data":{"active_cryptocurrencies":9479,"total_cryptocurrencies":35482,"active_market_pairs":106730,"active_exchanges":835,"total_exchanges":10795,"eth_dominance":11.849660203875,"btc_dominance":60.919076377554,"eth_dominance_yesterday":11.99202983,"btc_dominance_yesterday":60.67882891,"eth_dominance_24h_percentage_change":-0.142369626125,"btc_dominance_24h_percentage_change":0.240247467554,"defi_volume_24h":41851179123.549126,"defi_volume_24h_reported":89824858202.24266,"defi_market_cap":104294149581.20468,"defi_24h_percentage_change":-3.451600357577,"stablecoin_volume_24h":171592412151.98495,"stablecoin_volume_24h_reported":905006887174.3503,"stablecoin_market_cap":248672954889.68436,"stablecoin_24h_percentage_change":1.789992960494,"derivatives_volume_24h":1703274926576.428,"derivatives_volume_24h_reported":1703274926576.428,"derivatives_24h_percentage_change":-4.124852321167,"total_crypto_dex_currencies":18968008,"today_incremental_crypto_number":5,"past_24h_incremental_crypto_number":23225,"past_7d_incremental_crypto_number":155686,"past_30d_incremental_crypto_number":921345,"today_change_percent":0.010123331707,"tracked_yearly_number":{"maxIncrementalNumber":184087,"minIncrementalNumber":1921,"maxIncrementalDate":"2025-04-17T00:00:00.000Z","minIncrementalDate":"2025-08-01T00:00:00.000Z"},"quote":{"USD":{"total_market_cap":3787807900913.808,"total_volume_24h":178224728048.51,"total_volume_24h_reported":926022331891.45,"altcoin_volume_24h":102530012026.76535,"altcoin_volume_24h_reported":646438197743.882,"altcoin_market_cap":1480310312721.0872,"defi_volume_24h":41851179123.549126,"defi_volume_24h_reported":89824858202.24266,"defi_24h_percentage_change":-3.451600357577,"defi_market_cap":104294149581.20468,"stablecoin_volume_24h":171592412151.98495,"stablecoin_volume_24h_reported":905006887174.3503,"stablecoin_24h_percentage_change":1.789992960494,"stablecoin_market_cap":248672954889.68436,"derivatives_volume_24h":1703274926576.428,"derivatives_volume_24h_reported":1703274926576.428,"derivatives_24h_percentage_change":-4.124852321167,"total_market_cap_yesterday":3882752589208.477,"total_volume_24h_yesterday":172878726875.43,"total_market_cap_yesterday_percentage_change":-2.445293283907745,"total_volume_24h_yesterday_percentage_change":3.092341822329672,"last_updated":"2025-08-01T02:49:59.999Z"}},"last_updated":"2025-08-01T02:49:59.999Z"}}
{"status":{"timestamp":"2025-08-01T03:40:14.437Z","error_code":0,"error_message":null,"elapsed":27,"credit_count":1,"notice":null},"data":{"active_cryptocurrencies":9479,"total_cryptocurrencies":35482,"active_market_pairs":106728,"active_exchanges":834,"total_exchanges":10795,"eth_dominance":11.838224260701,"btc_dominance":60.915370322503,"eth_dominance_yesterday":11.99129638,"btc_dominance_yesterday":60.6537802,"eth_dominance_24h_percentage_change":-0.153072119299,"btc_dominance_24h_percentage_change":0.261590122503,"defi_volume_24h":41959212648.16827,"defi_volume_24h_reported":89972280449.37776,"defi_market_cap":104366852233.39806,"defi_24h_percentage_change":-2.875183436641,"stablecoin_volume_24h":173404180872.4244,"stablecoin_volume_24h_reported":906600676842.4697,"stablecoin_market_cap":248666546385.77518,"stablecoin_24h_percentage_change":2.315174653067,"derivatives_volume_24h":1706710148982.6855,"derivatives_volume_24h_reported":1706710148982.6855,"derivatives_24h_percentage_change":-1.732007559134,"total_crypto_dex_currencies":18968234,"today_incremental_crypto_number":5,"past_24h_incremental_crypto_number":23225,"past_7d_incremental_crypto_number":155912,"past_30d_incremental_crypto_number":921571,"today_change_percent":0.01131493221,"tracked_yearly_number":{"maxIncrementalNumber":184087,"minIncrementalNumber":2147,"maxIncrementalDate":"2025-04-17T00:00:00.000Z","minIncrementalDate":"2025-08-01T00:00:00.000Z"},"quote":{"USD":{"total_market_cap":3786093243735.363,"total_volume_24h":180288378501.72,"total_volume_24h_reported":927547531874.59,"altcoin_volume_24h":103417330902.07986,"altcoin_volume_24h_reported":646395067047.377,"altcoin_market_cap":1479780523558.6887,"defi_volume_24h":41959212648.16827,"defi_volume_24h_reported":89972280449.37776,"defi_24h_percentage_change":-2.875183436641,"defi_market_cap":104366852233.39806,"stablecoin_volume_24h":173404180872.4244,"stablecoin_volume_24h_reported":906600676842.4697,"stablecoin_24h_percentage_change":2.315174653067,"stablecoin_market_cap":248666546385.77518,"derivatives_volume_24h":1706710148982.6855,"derivatives_volume_24h_reported":1706710148982.6855,"derivatives_24h_percentage_change":-1.732007559134,"total_market_cap_yesterday":3885720449266.003,"total_volume_24h_yesterday":174635831021.54,"total_market_cap_yesterday_percentage_change":-2.563931369521427,"total_volume_24h_yesterday_percentage_change":3.2367627233856666,"last_updated":"2025-08-01T03:37:59.999Z"}},"last_updated":"2025-08-01T03:37:59.999Z"}}
{"status":{"timestamp":"2025-08-01T04:26:46.013Z","error_code":0,"error_message":null,"elapsed":27,"credit_count":1,"notice":null},"data":{"active_cryptocurrencies":9483,"total_cryptocurrencies":35484,"active_market_pairs":106737,"active_exchanges":834,"total_exchanges":10795,"eth_dominance":11.810696447054,"btc_dominance":61.001146713318,"eth_dominance_yesterday":11.98706806,"btc_dominance_yesterday":60.65350601,"eth_dominance_24h_percentage_change":-0.176371612946,"btc_dominance_24h_percentage_change":0.347640703318,"defi_volume_24h":42026857072.23248,"defi_volume_24h_reported":90242917096.42714,"defi_market_cap":103247143092.66153,"defi_24h_percentage_change":-2.406814914909,"stablecoin_volume_24h":173823417382.1717,"stablecoin_volume_24h_reported":913516131511.7166,"stablecoin_market_cap":248618968882.8395,"stablecoin_24h_percentage_change":2.736859163288,"derivatives_volume_24h":1716279375161.8618,"derivatives_volume_24h_reported":1716279375161.8618,"derivatives_24h_percentage_change":-0.646144205072,"total_crypto_dex_currencies":18968234,"today_incremental_crypto_number":5,"past_24h_incremental_crypto_number":23225,"past_7d_incremental_crypto_number":155912,"past_30d_incremental_crypto_number":921571,"today_change_percent":0.01131493221,"tracked_yearly_number":{"maxIncrementalNumber":184087,"minIncrementalNumber":2147,"maxIncrementalDate":"2025-04-17T00:00:00.000Z","minIncrementalDate":"2025-08-01T00:00:00.000Z"},"quote":{"USD":{"total_market_cap":3766031942204.8438,"total_volume_24h":180035701014.14,"total_volume_24h_reported":934511717801.31,"altcoin_volume_24h":103745544707.28828,"altcoin_volume_24h_reported":652235616542.0968,"altcoin_market_cap":1468709271870.0403,"defi_volume_24h":42026857072.23248,"defi_volume_24h_reported":90242917096.42714,"defi_24h_percentage_change":-2.406814914909,"defi_market_cap":103247143092.66153,"stablecoin_volume_24h":173823417382.1717,"stablecoin_volume_24h_reported":913516131511.7166,"stablecoin_24h_percentage_change":2.736859163288,"stablecoin_market_cap":248618968882.8395,"derivatives_volume_24h":1716279375161.8618,"derivatives_volume_24h_reported":1716279375161.8618,"derivatives_24h_percentage_change":-0.646144205072,"total_market_cap_yesterday":3884828598174.3965,"total_volume_24h_yesterday":174146922593.47,"total_market_cap_yesterday_percentage_change":-3.0579638964092055,"total_volume_24h_yesterday_percentage_change":3.381500133893738,"last_updated":"2025-08-01T04:24:59.999Z"}},"last_updated":"2025-08-01T04:24:59.999Z"}}
{"status":{"timestamp":"2025-08-01T05:13:20.854Z","error_code":0,"error_message":null,"elapsed":116,"credit_count":1,"notice":null},"data":{"active_cryptocurrencies":9483,"total_cryptocurrencies":35484,"active_market_pairs":106737,"active_exchanges":834,"total_exchanges":10795,"eth_dominance":11.799367778267,"btc_dominance":61.061349927818,"eth_dominance_yesterday":11.9901494,"btc_dominance_yesterday":60.59966964,"eth_dominance_24h_percentage_change":-0.190781621733,"btc_dominance_24h_percentage_change":0.461680287818,"defi_volume_24h":42120778227.63221,"defi_volume_24h_reported":90155376317.73695,"defi_market_cap":103224620609.99773,"defi_24h_percentage_change":-2.251073223368,"stablecoin_volume_24h":173383703599.2045,"stablecoin_volume_24h_reported":914537952454.8192,"stablecoin_market_cap":248594280576.6766,"stablecoin_24h_percentage_change":2.497854978859,"derivatives_volume_24h":1721283644549.8718,"derivatives_volume_24h_reported":1721283644549.8718,"derivatives_24h_percentage_change":-0.377789111704,"total_crypto_dex_currencies":18968234,"today_incremental_crypto_number":5,"past_24h_incremental_crypto_number":23225,"past_7d_incremental_crypto_number":155912,"past_30d_incremental_crypto_number":921571,"today_change_percent":0.01131493221,"tracked_yearly_number":{"maxIncrementalNumber":184087,"minIncrementalNumber":2147,"maxIncrementalDate":"2025-04-17T00:00:00.000Z","minIncrementalDate":"2025-08-01T00:00:00.000Z"},"quote":{"USD":{"total_market_cap":3777202751413.7754,"total_volume_24h":179169592410.01,"total_volume_24h_reported":935592818604.1,"altcoin_volume_24h":103782090621.54645,"altcoin_volume_24h_reported":652771650062.9711,"altcoin_market_cap":1470791761889.8245,"defi_volume_24h":42120778227.63221,"defi_volume_24h_reported":90155376317.73695,"defi_24h_percentage_change":-2.251073223368,"defi_market_cap":103224620609.99773,"stablecoin_volume_24h":173383703599.2045,"stablecoin_volume_24h_reported":914537952454.8192,"stablecoin_24h_percentage_change":2.497854978859,"stablecoin_market_cap":248594280576.6766,"derivatives_volume_24h":1721283644549.8718,"derivatives_volume_24h_reported":1721283644549.8718,"derivatives_24h_percentage_change":-0.377789111704,"total_market_cap_yesterday":3888289237482.896,"total_volume_24h_yesterday":174460278183.32,"total_market_cap_yesterday_percentage_change":-2.8569501722827937,"total_volume_24h_yesterday_percentage_change":2.699361869491895,"last_updated":"2025-08-01T05:11:59.999Z"}},"last_updated":"2025-08-01T05:11:59.999Z"}}
{"status":{"timestamp":"2025-08-01T06:08:11.966Z","error_code":0,"error_message":null,"elapsed":14,"credit_count":1,"notice":null},"data":{"active_cryptocurrencies":9485,"total_cryptocurrencies":35486,"active_market_pairs":106753,"active_exchanges":834,"total_exchanges":10795,"eth_dominance":11.78021353823,"btc_dominance":61.134833872285,"eth_dominance_yesterday":11.9877932,"btc_dominance_yesterday":60.59930869,"eth_dominance_24h_percentage_change":-0.20757966177,"btc_dominance_24h_percentage_change":0.535525182285,"defi_volume_24h":42320042930.71414,"defi_volume_24h_reported":90708990911.36674,"defi_market_cap":102451169927.5676,"defi_24h_percentage_change":-1.205891579844,"stablecoin_volume_24h":175475776524.5853,"stablecoin_volume_24h_reported":923736647754.2524,"stablecoin_market_cap":248593779468.08713,"stablecoin_24h_percentage_change":3.521713082686,"derivatives_volume_24h":1736927401560.3167,"derivatives_volume_24h_reported":1736927401560.3167,"derivatives_24h_percentage_change":1.617965065008,"total_crypto_dex_currencies":18968234,"today_incremental_crypto_number":5,"past_24h_incremental_crypto_number":23225,"past_7d_incremental_crypto_number":155912,"past_30d_incremental_crypto_number":921571,"today_change_percent":0.01131493221,"tracked_yearly_number":{"maxIncrementalNumber":184087,"minIncrementalNumber":2147,"maxIncrementalDate":"2025-04-17T00:00:00.000Z","minIncrementalDate":"2025-08-01T00:00:00.000Z"},"quote":{"USD":{"total_market_cap":3759927238305.82,"total_volume_24h":181614462628.6,"total_volume_24h_reported":944956102775.41,"altcoin_volume_24h":104153092556.76843,"altcoin_volume_24h_reported":659081676388.1483,"altcoin_market_cap":1461301967448.7532,"defi_volume_24h":42320042930.71414,"defi_volume_24h_reported":90708990911.36674,"defi_24h_percentage_change":-1.205891579844,"defi_market_cap":102451169927.5676,"stablecoin_volume_24h":175475776524.5853,"stablecoin_volume_24h_reported":923736647754.2524,"stablecoin_24h_percentage_change":3.521713082686,"stablecoin_market_cap":248593779468.08713,"derivatives_volume_24h":1736927401560.3167,"derivatives_volume_24h_reported":1736927401560.3167,"derivatives_24h_percentage_change":1.617965065008,"total_market_cap_yesterday":3886757132305.21,"total_volume_24h_yesterday":174851555393.9,"total_market_cap_yesterday_percentage_change":-3.2631288676421235,"total_volume_24h_yesterday_percentage_change":3.8677992995056485,"last_updated":"2025-08-01T06:05:59.999Z"}},"last_updated":"2025-08-01T06:05:59.999Z"}}
{"status":{"timestamp":"2025-08-01T07:08:59.163Z","error_code":0,"error_message":null,"elapsed":21,"credit_count":1,"notice":null},"data":{"active_cryptocurrencies":9485,"total_cryptocurrencies":35486,"active_market_pairs":106749,"active_exchanges":834,"total_exchanges":10795,"eth_dominance":11.766383946087,"btc_dominance":61.061219319379,"eth_dominance_yesterday":11.98719089,"btc_dominance_yesterday":60.62149732,"eth_dominance_24h_percentage_change":-0.220806943913,"btc_dominance_24h_percentage_change":0.439721999379,"defi_volume_24h":42403614846.661224,"defi_volume_24h_reported":91052148844.92313,"defi_market_cap":102475170405.353,"defi_24h_percentage_change":-1.717559608504,"stablecoin_volume_24h":175922662892.3453,"stablecoin_volume_24h_reported":935487636092.6011,"stablecoin_market_cap":248550717506.75607,"stablecoin_24h_percentage_change":3.733835637072,"derivatives_volume_24h":1761896443267.7031,"derivatives_volume_24h_reported":1761896443267.7031,"derivatives_24h_percentage_change":6.281907336905,"total_crypto_dex_currencies":18968234,"today_incremental_crypto_number":5,"past_24h_incremental_crypto_number":23225,"past_7d_incremental_crypto_number":155912,"past_30d_incremental_crypto_number":921571,"today_change_percent":0.01131493221,"tracked_yearly_number":{"maxIncrementalNumber":184087,"minIncrementalNumber":2147,"maxIncrementalDate":"2025-04-17T00:00:00.000Z","minIncrementalDate":"2025-08-01T00:00:00.000Z"},"quote":{"USD":{"total_market_cap":3751182660572.345,"total_volume_24h":182499238058.94,"total_volume_24h_reported":956955775039.13,"altcoin_volume_24h":105338365674.50351,"altcoin_volume_24h_reported":669372914771.6294,"altcoin_market_cap":1460664789129.759,"defi_volume_24h":42403614846.661224,"defi_volume_24h_reported":91052148844.92313,"defi_24h_percentage_change":-1.717559608504,"defi_market_cap":102475170405.353,"stablecoin_volume_24h":175922662892.3453,"stablecoin_volume_24h_reported":935487636092.6011,"stablecoin_24h_percentage_change":3.733835637072,"stablecoin_market_cap":248550717506.75607,"derivatives_volume_24h":1761896443267.7031,"derivatives_volume_24h_reported":1761896443267.7031,"derivatives_24h_percentage_change":6.281907336905,"total_market_cap_yesterday":3894011750445.1943,"total_volume_24h_yesterday":175196013896.49,"total_market_cap_yesterday_percentage_change":-3.6679162526029785,"total_volume_24h_yesterday_percentage_change":4.1686017849498285,"last_updated":"2025-08-01T07:06:59.999Z"}},"last_updated":"2025-08-01T07:06:59.999Z"}}
{"status":{"timestamp":"2025-08-01T08:06:42.849Z","error_code":0,"error_message":null,"elapsed":32,"credit_count":1,"notice":null},"data":{"active_cryptocurrencies":9483,"total_cryptocurrencies":35486,"active_market_pairs":106752,"active_exchanges":834,"total_exchanges":10795,"eth_dominance":11.72701711944,"btc_dominance":61.136090925295,"eth_dominance_yesterday":11.9635069,"btc_dominance_yesterday":60.62294072,"eth_dominance_24h_percentage_change":-0.23648978056,"btc_dominance_24h_percentage_change":0.513150205295,"defi_volume_24h":42461385123.43419,"defi_volume_24h_reported":91609305254.2744,"defi_market_cap":101867735685.96962,"defi_24h_percentage_change":-1.319272925221,"stablecoin_volume_24h":179175288297.56467,"stablecoin_volume_24h_reported":954110331261.2106,"stablecoin_market_cap":248509638404.5937,"stablecoin_24h_percentage_change":4.891235461768,"derivatives_volume_24h":1804753691738.5498,"derivatives_volume_24h_reported":1804753691738.5498,"derivatives_24h_percentage_change":9.027123856007,"total_crypto_dex_currencies":18968234,"today_incremental_crypto_number":5,"past_24h_incremental_crypto_number":23225,"past_7d_incremental_crypto_number":155912,"past_30d_incremental_crypto_number":921571,"today_change_percent":0.01131493221,"tracked_yearly_number":{"maxIncrementalNumber":184087,"minIncrementalNumber":2147,"maxIncrementalDate":"2025-04-17T00:00:00.000Z","minIncrementalDate":"2025-08-01T00:00:00.000Z"},"quote":{"USD":{"total_market_cap":3736481911417.64,"total_volume_24h":186248424363.14,"total_volume_24h_reported":976194019723.41,"altcoin_volume_24h":106900016932.46425,"altcoin_volume_24h_reported":682070332067.1606,"altcoin_market_cap":1452142932646.1523,"defi_volume_24h":42461385123.43419,"defi_volume_24h_reported":91609305254.2744,"defi_24h_percentage_change":-1.319272925221,"defi_market_cap":101867735685.96962,"stablecoin_volume_24h":179175288297.56467,"stablecoin_volume_24h_reported":954110331261.2106,"stablecoin_24h_percentage_change":4.891235461768,"stablecoin_market_cap":248509638404.5937,"derivatives_volume_24h":1804753691738.5498,"derivatives_volume_24h_reported":1804753691738.5498,"derivatives_24h_percentage_change":9.027123856007,"total_market_cap_yesterday":3894991785123.4116,"total_volume_24h_yesterday":176104407037.3,"total_market_cap_yesterday_percentage_change":-4.069581720587607,"total_volume_24h_yesterday_percentage_change":5.7602291143636535,"last_updated":"2025-08-01T08:04:59.999Z"}},"last_updated":"2025-08-01T08:04:59.999Z"}}
{"status":{"timestamp":"2025-08-01T09:07:59.581Z","error_code":0,"error_message":null,"elapsed":16,"credit_count":1,"notice":null},"data":{"active_cryptocurrencies":9487,"total_cryptocurrencies":35493,"active_market_pairs":106738,"active_exchanges":834,"total_exchanges":10795,"eth_dominance":11.704688701095,"btc_dominance":61.197062536812,"eth_dominance_yesterday":11.96425389,"btc_dominance_yesterday":60.55931329,"eth_dominance_24h_percentage_change":-0.259565188905,"btc_dominance_24h_percentage_change":0.637749246812,"defi_volume_24h":43056667046.58401,"defi_volume_24h_reported":93914313020.02211,"defi_market_cap":101708859920.71611,"defi_24h_percentage_change":0.645524443003,"stablecoin_volume_24h":186160385002.08823,"stablecoin_volume_24h_reported":1003354799372.6573,"stablecoin_market_cap":248557276769.7795,"stablecoin_24h_percentage_change":9.433538686756,"derivatives_volume_24h":1892406330023.4707,"derivatives_volume_24h_reported":1892406330023.4707,"derivatives_24h_percentage_change":15.013526969459,"total_crypto_dex_currencies":18968234,"today_incremental_crypto_number":5,"past_24h_incremental_crypto_number":23225,"past_7d_incremental_crypto_number":155912,"past_30d_incremental_crypto_number":921571,"today_change_percent":0.01131493221,"tracked_yearly_number":{"maxIncrementalNumber":184087,"minIncrementalNumber":2147,"maxIncrementalDate":"2025-04-17T00:00:00.000Z","minIncrementalDate":"2025-08-01T00:00:00.000Z"},"quote":{"USD":{"total_market_cap":3740623198458.0635,"total_volume_24h":192426435041.1,"total_volume_24h_reported":1026616772896.51,"altcoin_volume_24h":111262254327.42128,"altcoin_volume_24h_reported":717745028195.8307,"altcoin_market_cap":1451471680431.1968,"defi_volume_24h":43056667046.58401,"defi_volume_24h_reported":93914313020.02211,"defi_24h_percentage_change":0.645524443003,"defi_market_cap":101708859920.71611,"stablecoin_volume_24h":186160385002.08823,"stablecoin_volume_24h_reported":1003354799372.6573,"stablecoin_24h_percentage_change":9.433538686756,"stablecoin_market_cap":248557276769.7795,"derivatives_volume_24h":1892406330023.4707,"derivatives_volume_24h_reported":1892406330023.4707,"derivatives_24h_percentage_change":15.013526969459,"total_market_cap_yesterday":3894493746280.5225,"total_volume_24h_yesterday":174796301342.91,"total_market_cap_yesterday_percentage_change":-3.9509768880593157,"total_volume_24h_yesterday_percentage_change":10.086102258882335,"last_updated":"2025-08-01T09:06:59.999Z"}},"last_updated":"2025-08-01T09:06:59.999Z"}}
{"status":{"timestamp":"2025-08-01T10:05:19.863Z","error_code":0,"error_message":null,"elapsed":293,"credit_count":1,"notice":null},"data":{"active_cryptocurrencies":9487,"total_cryptocurrencies":35493,"active_market_pairs":106758,"active_exchanges":834,"total_exchanges":10795,"eth_dominance":11.700354736147,"btc_dominance":61.244576918463,"eth_dominance_yesterday":11.95518824,"btc_dominance_yesterday":60.54183836,"eth_dominance_24h_percentage_change":-0.254833503853,"btc_dominance_24h_percentage_change":0.702738558463,"defi_volume_24h":43577421595.53604,"defi_volume_24h_reported":94720389830.60538,"defi_market_cap":101050068269.27676,"defi_24h_percentage_change":3.251438888485,"stablecoin_volume_24h":188906425875.08408,"stablecoin_volume_24h_reported":1016262861523.1864,"stablecoin_market_cap":248540828440.99677,"stablecoin_24h_percentage_change":12.484009194134,"derivatives_volume_24h":1911128644500.5405,"derivatives_volume_24h_reported":1911128644500.5405,"derivatives_24h_percentage_change":17.173957016881,"total_crypto_dex_currencies":18968234,"today_incremental_crypto_number":5,"past_24h_incremental_crypto_number":23225,"past_7d_incremental_crypto_number":155912,"past_30d_incremental_crypto_number":921571,"today_change_percent":0.01131493221,"tracked_yearly_number":{"maxIncrementalNumber":184087,"minIncrementalNumber":2147,"maxIncrementalDate":"2025-04-17T00:00:00.000Z","minIncrementalDate":"2025-08-01T00:00:00.000Z"},"quote":{"USD":{"total_market_cap":3735020465159.849,"total_volume_24h":195447755436.07,"total_volume_24h_reported":1039518534081.44,"altcoin_volume_24h":112205516779.85497,"altcoin_volume_24h_reported":724764265503.77,"altcoin_market_cap":1447522983454.6738,"defi_volume_24h":43577421595.53604,"defi_volume_24h_reported":94720389830.60538,"defi_24h_percentage_change":3.251438888485,"defi_market_cap":101050068269.27676,"stablecoin_volume_24h":188906425875.08408,"stablecoin_volume_24h_reported":1016262861523.1864,"stablecoin_24h_percentage_change":12.484009194134,"stablecoin_market_cap":248540828440.99677,"derivatives_volume_24h":1911128644500.5405,"derivatives_volume_24h_reported":1911128644500.5405,"derivatives_24h_percentage_change":17.173957016881,"total_market_cap_yesterday":3899372581548.107,"total_volume_24h_yesterday":173162094514.39,"total_market_cap_yesterday_percentage_change":-4.214834898464815,"total_volume_24h_yesterday_percentage_change":12.869826380985486,"last_updated":"2025-08-01T10:03:59.999Z"}},"last_updated":"2025-08-01T10:03:59.999Z"}}
{"status":{"timestamp":"2025-08-01T11:04:47.385Z","error_code":0,"error_message":null,"elapsed":16,"credit_count":1,"notice":null},"data":{"active_cryptocurrencies":9488,"total_cryptocurrencies":35493,"active_market_pairs":106762,"active_exchanges":834,"total_exchanges":10795,"eth_dominance":11.676088932985,"btc_dominance":61.153896970094,"eth_dominance_yesterday":11.9542648,"btc_dominance_yesterday":60.57121667,"eth_dominance_24h_percentage_change":-0.278175867015,"btc_dominance_24h_percentage_change":0.582680300094,"defi_volume_24h":43406679495.46242,"defi_volume_24h_reported":94963534284.613,"defi_market_cap":101502907767.15367,"defi_24h_percentage_change":2.713703302578,"stablecoin_volume_24h":190007458749.84448,"stablecoin_volume_24h_reported":1022278781062.9261,"stablecoin_market_cap":248554851951.02786,"stablecoin_24h_percentage_change":13.169200670521,"derivatives_volume_24h":1924120872115.8516,"derivatives_volume_24h_reported":1924120872115.8516,"derivatives_24h_percentage_change":19.118196819815,"total_crypto_dex_currencies":18968234,"today_incremental_crypto_number":5,"past_24h_incremental_crypto_number":23225,"past_7d_incremental_crypto_number":155912,"past_30d_incremental_crypto_number":921571,"today_change_percent":0.01131493221,"tracked_yearly_number":{"maxIncrementalNumber":184087,"minIncrementalNumber":2147,"maxIncrementalDate":"2025-04-17T00:00:00.000Z","minIncrementalDate":"2025-08-01T00:00:00.000Z"},"quote":{"USD":{"total_market_cap":3731479453191.9146,"total_volume_24h":196973719960.23,"total_volume_24h_reported":1069390017793.49,"altcoin_volume_24h":112633622727.45815,"altcoin_volume_24h_reported":727360106290.8331,"altcoin_market_cap":1449534352926.7139,"defi_volume_24h":43406679495.46242,"defi_volume_24h_reported":94963534284.613,"defi_24h_percentage_change":2.713703302578,"defi_market_cap":101502907767.15367,"stablecoin_volume_24h":190007458749.84448,"stablecoin_volume_24h_reported":1022278781062.9261,"stablecoin_24h_percentage_change":13.169200670521,"stablecoin_market_cap":248554851951.02786,"derivatives_volume_24h":1924120872115.8516,"derivatives_volume_24h_reported":1924120872115.8516,"derivatives_24h_percentage_change":19.118196819815,"total_market_cap_yesterday":3894162227584.671,"total_volume_24h_yesterday":172134107810.66,"total_market_cap_yesterday_percentage_change":-4.177606501351633,"total_volume_24h_yesterday_percentage_change":14.430383649992535,"last_updated":"2025-08-01T11:02:59.999Z"}},"last_updated":"2025-08-01T11:02:59.999Z"}}
{"status":{"timestamp":"2025-08-01T12:08:20.939Z","error_code":0,"error_message":null,"elapsed":24,"credit_count":1,"notice":null},"data":{"active_cryptocurrencies":9488,"total_cryptocurrencies":35494,"active_market_pairs":106767,"active_exchanges":834,"total_exchanges":10795,"eth_dominance":11.722891495967,"btc_dominance":61.142247978905,"eth_dominance_yesterday":11.93198301,"btc_dominance_yesterday":60.6465922,"eth_dominance_24h_percentage_change":-0.209091514033,"btc_dominance_24h_percentage_change":0.495655778905,"defi_volume_24h":43410270680.85049,"defi_volume_24h_reported":95214367897.24956,"defi_market_cap":102357213743.81825,"defi_24h_percentage_change":3.79087069955,"stablecoin_volume_24h":189852288463.64755,"stablecoin_volume_24h_reported":1021873796996.6354,"stablecoin_market_cap":248576332801.03696,"stablecoin_24h_percentage_change":15.003714110983,"derivatives_volume_24h":1930285433381.5022,"derivatives_volume_24h_reported":1930285433381.5022,"derivatives_24h_percentage_change":22.055800339631,"total_crypto_dex_currencies":18968234,"today_incremental_crypto_number":5,"past_24h_incremental_crypto_number":23225,"past_7d_incremental_crypto_number":155912,"past_30d_incremental_crypto_number":921571,"today_change_percent":0.01131493221,"tracked_yearly_number":{"maxIncrementalNumber":184087,"minIncrementalNumber":2147,"maxIncrementalDate":"2025-04-17T00:00:00.000Z","minIncrementalDate":"2025-08-01T00:00:00.000Z"},"quote":{"USD":{"total_market_cap":3755642043111.417,"total_volume_24h":196413424221.94,"total_volume_24h_reported":1045312812104.05,"altcoin_volume_24h":112275526882.16537,"altcoin_volume_24h_reported":724102907446.7847,"altcoin_market_cap":1459358071912.216,"defi_volume_24h":43410270680.85049,"defi_volume_24h_reported":95214367897.24956,"defi_24h_percentage_change":3.79087069955,"defi_market_cap":102357213743.81825,"stablecoin_volume_24h":189852288463.64755,"stablecoin_volume_24h_reported":1021873796996.6354,"stablecoin_24h_percentage_change":15.003714110983,"stablecoin_market_cap":248576332801.03696,"derivatives_volume_24h":1930285433381.5022,"derivatives_volume_24h_reported":1930285433381.5022,"derivatives_24h_percentage_change":22.055800339631,"total_market_cap_yesterday":3883747464617.3457,"total_volume_24h_yesterday":170085258980.82,"total_market_cap_yesterday_percentage_change":-3.2985002931582414,"total_volume_24h_yesterday_percentage_change":15.479392746251435,"last_updated":"2025-08-01T12:05:59.999Z"}},"last_updated":"2025-08-01T12:05:59.999Z"}}
{"status":{"timestamp":"2025-08-01T13:16:27.835Z","error_code":0,"error_message":null,"elapsed":33,"credit_count":1,"notice":null},"data":{"active_cryptocurrencies":9488,"total_cryptocurrencies":35494,"active_market_pairs":106777,"active_exchanges":834,"total_exchanges":10795,"eth_dominance":11.74433277243,"btc_dominance":61.126995736836,"eth_dominance_yesterday":11.88077017,"btc_dominance_yesterday":60.84937701,"eth_dominance_24h_percentage_change":-0.13643739757,"btc_dominance_24h_percentage_change":0.277618726836,"defi_volume_24h":43654835526.94048,"defi_volume_24h_reported":96108396237.78632,"defi_market_cap":102919894994.4001,"defi_24h_percentage_change":4.553312151556,"stablecoin_volume_24h":192614965846.42197,"stablecoin_volume_24h_reported":1040405404251.3657,"stablecoin_market_cap":248644133528.61197,"stablecoin_24h_percentage_change":17.794393241106,"derivatives_volume_24h":1962422738161.0508,"derivatives_volume_24h_reported":1962422738161.0508,"derivatives_24h_percentage_change":24.889231277683,"total_crypto_dex_currencies":18968234,"today_incremental_crypto_number":5,"past_24h_incremental_crypto_number":23225,"past_7d_incremental_crypto_number":155912,"past_30d_incremental_crypto_number":921571,"today_change_percent":0.01131493221,"tracked_yearly_number":{"maxIncrementalNumber":184087,"minIncrementalNumber":2147,"maxIncrementalDate":"2025-04-17T00:00:00.000Z","minIncrementalDate":"2025-08-01T00:00:00.000Z"},"quote":{"USD":{"total_market_cap":3772877461316.784,"total_volume_24h":199117235019.37,"total_volume_24h_reported":1064572777752.71,"altcoin_volume_24h":112858068936.75543,"altcoin_volume_24h_reported":733598001448.2712,"altcoin_market_cap":1466630816381.6255,"defi_volume_24h":43654835526.94048,"defi_volume_24h_reported":96108396237.78632,"defi_24h_percentage_change":4.553312151556,"defi_market_cap":102919894994.4001,"stablecoin_volume_24h":192614965846.42197,"stablecoin_volume_24h_reported":1040405404251.3657,"stablecoin_24h_percentage_change":17.794393241106,"stablecoin_market_cap":248644133528.61197,"derivatives_volume_24h":1962422738161.0508,"derivatives_volume_24h_reported":1962422738161.0508,"derivatives_24h_percentage_change":24.889231277683,"total_market_cap_yesterday":3868414132294.7847,"total_volume_24h_yesterday":167201253337.87,"total_market_cap_yesterday_percentage_change":-2.4696598582977174,"total_volume_24h_yesterday_percentage_change":19.088362703242495,"last_updated":"2025-08-01T13:14:59.999Z"}},"last_updated":"2025-08-01T13:14:59.999Z"}}
{"status":{"timestamp":"2025-08-01T14:06:05.045Z","error_code":0,"error_message":null,"elapsed":20,"credit_count":1,"notice":null},"data":{"active_cryptocurrencies":9488,"total_cryptocurrencies":35494,"active_market_pairs":106780,"active_exchanges":834,"total_exchanges":10795,"eth_dominance":11.640267818377,"btc_dominance":61.228949877087,"eth_dominance_yesterday":11.86367203,"btc_dominance_yesterday":60.87605936,"eth_dominance_24h_percentage_change":-0.223404211623,"btc_dominance_24h_percentage_change":0.352890517087,"defi_volume_24h":43003945713.75784,"defi_volume_24h_reported":95614529890.38663,"defi_market_cap":100140102547.92183,"defi_24h_percentage_change":2.299178333117,"stablecoin_volume_24h":194134466339.3281,"stablecoin_volume_24h_reported":1045546317619.9177,"stablecoin_market_cap":248601842345.6673,"stablecoin_24h_percentage_change":17.936431614291,"derivatives_volume_24h":1971336317709.4055,"derivatives_volume_24h_reported":1971336317709.4055,"derivatives_24h_percentage_change":23.017237497506,"total_crypto_dex_currencies":18968234,"today_incremental_crypto_number":5,"past_24h_incremental_crypto_number":23225,"past_7d_incremental_crypto_number":155912,"past_30d_incremental_crypto_number":921571,"today_change_percent":0.01131493221,"tracked_yearly_number":{"maxIncrementalNumber":184087,"minIncrementalNumber":2147,"maxIncrementalDate":"2025-04-17T00:00:00.000Z","minIncrementalDate":"2025-08-01T00:00:00.000Z"},"quote":{"USD":{"total_market_cap":3712220461442.1416,"total_volume_24h":200415690273.76,"total_volume_24h_reported":1069847711462.77,"altcoin_volume_24h":113463266749.80544,"altcoin_volume_24h_reported":734732484728.2413,"altcoin_market_cap":1439266855778.7644,"defi_volume_24h":43003945713.75784,"defi_volume_24h_reported":95614529890.38663,"defi_24h_percentage_change":2.299178333117,"defi_market_cap":100140102547.92183,"stablecoin_volume_24h":194134466339.3281,"stablecoin_volume_24h_reported":1045546317619.9177,"stablecoin_24h_percentage_change":17.936431614291,"stablecoin_market_cap":248601842345.6673,"derivatives_volume_24h":1971336317709.4055,"derivatives_volume_24h_reported":1971336317709.4055,"derivatives_24h_percentage_change":23.017237497506,"total_market_cap_yesterday":3872783482913.1772,"total_volume_24h_yesterday":169382545693.09,"total_market_cap_yesterday_percentage_change":-4.145933336563843,"total_volume_24h_yesterday_percentage_change":18.321335562461087,"last_updated":"2025-08-01T14:03:59.999Z"}},"last_updated":"2025-08-01T14:03:59.999Z"}}
{"status":{"timestamp":"2025-08-01T15:05:11.525Z","error_code":0,"error_message":null,"elapsed":27,"credit_count":1,"notice":null},"data":{"active_cryptocurrencies":9488,"total_cryptocurrencies":35494,"active_market_pairs":106785,"active_exchanges":834,"total_exchanges":10795,"eth_dominance":11.639490510643,"btc_dominance":61.097136385788,"eth_dominance_yesterday":11.82800413,"btc_dominance_yesterday":60.99497419,"eth_dominance_24h_percentage_change":-0.188513619357,"btc_dominance_24h_percentage_change":0.102162195788,"defi_volume_24h":43568264310.71184,"defi_volume_24h_reported":97180887153.59572,"defi_market_cap":102762165144.33894,"defi_24h_percentage_change":3.264765017696,"stablecoin_volume_24h":198036462993.71112,"stablecoin_volume_24h_reported":1075065131930.919,"stablecoin_market_cap":248567579911.54034,"stablecoin_24h_percentage_change":20.189324481608,"derivatives_volume_24h":2028156530370.795,"derivatives_volume_24h_reported":2028156530370.795,"derivatives_24h_percentage_change":26.139854062041,"total_crypto_dex_currencies":18968234,"today_incremental_crypto_number":5,"past_24h_incremental_crypto_number":23225,"past_7d_incremental_crypto_number":155912,"past_30d_incremental_crypto_number":921571,"today_change_percent":0.01131493221,"tracked_yearly_number":{"maxIncrementalNumber":184087,"minIncrementalNumber":2147,"maxIncrementalDate":"2025-04-17T00:00:00.000Z","minIncrementalDate":"2025-08-01T00:00:00.000Z"},"quote":{"USD":{"total_market_cap":3761803277616.5293,"total_volume_24h":205491252857.02,"total_volume_24h_reported":1100252441952.83,"altcoin_volume_24h":115090196504.99057,"altcoin_volume_24h_reported":749353107320.1499,"altcoin_market_cap":1463449198526.1282,"defi_volume_24h":43568264310.71184,"defi_volume_24h_reported":97180887153.59572,"defi_24h_percentage_change":3.264765017696,"defi_market_cap":102762165144.33894,"stablecoin_volume_24h":198036462993.71112,"stablecoin_volume_24h_reported":1075065131930.919,"stablecoin_24h_percentage_change":20.189324481608,"stablecoin_market_cap":248567579911.54034,"derivatives_volume_24h":2028156530370.795,"derivatives_volume_24h_reported":2028156530370.795,"derivatives_24h_percentage_change":26.139854062041,"total_market_cap_yesterday":3854407902193.1157,"total_volume_24h_yesterday":169510493798.65,"total_market_cap_yesterday_percentage_change":-2.4025642050986704,"total_volume_24h_yesterday_percentage_change":21.226272339875948,"last_updated":"2025-08-01T15:02:59.999Z"}},"last_updated":"2025-08-01T15:02:59.999Z"}}
{"status":{"timestamp":"2025-08-01T16:05:43.134Z","error_code":0,"error_message":null,"elapsed":66,"credit_count":1,"notice":null},"data":{"active_cryptocurrencies":9489,"total_cryptocurrencies":35496,"active_market_pairs":106787,"active_exchanges":834,"total_exchanges":10795,"eth_dominance":11.614664079854,"btc_dominance":61.149459418463,"eth_dominance_yesterday":11.84501899,"btc_dominance_yesterday":60.91818911,"eth_dominance_24h_percentage_change":-0.230354910146,"btc_dominance_24h_percentage_change":0.231270308463,"defi_volume_24h":43464827072.48431,"defi_volume_24h_reported":97357446296.23764,"defi_market_cap":102240836230.01646,"defi_24h_percentage_change":3.285419613914,"stablecoin_volume_24h":197791032500.10712,"stablecoin_volume_24h_reported":1085942208783.0483,"stablecoin_market_cap":248591528281.66934,"stablecoin_24h_percentage_change":20.118871515637,"derivatives_volume_24h":2043144774792.0684,"derivatives_volume_24h_reported":2043144774792.0684,"derivatives_24h_percentage_change":35.106212909911,"total_crypto_dex_currencies":18968234,"today_incremental_crypto_number":5,"past_24h_incremental_crypto_number":23225,"past_7d_incremental_crypto_number":155912,"past_30d_incremental_crypto_number":921571,"today_change_percent":0.01131493221,"tracked_yearly_number":{"maxIncrementalNumber":184087,"minIncrementalNumber":2147,"maxIncrementalDate":"2025-04-17T00:00:00.000Z","minIncrementalDate":"2025-08-01T00:00:00.000Z"},"quote":{"USD":{"total_market_cap":3755634523926.4756,"total_volume_24h":205318146028.83,"total_volume_24h_reported":1111524078597.39,"altcoin_volume_24h":114640104794.53937,"altcoin_volume_24h_reported":754130348324.805,"altcoin_market_cap":1459084314812.2712,"defi_volume_24h":43464827072.48431,"defi_volume_24h_reported":97357446296.23764,"defi_24h_percentage_change":3.285419613914,"defi_market_cap":102240836230.01646,"stablecoin_volume_24h":197791032500.10712,"stablecoin_volume_24h_reported":1085942208783.0483,"stablecoin_24h_percentage_change":20.118871515637,"stablecoin_market_cap":248591528281.66934,"derivatives_volume_24h":2043144774792.0684,"derivatives_volume_24h_reported":2043144774792.0684,"derivatives_24h_percentage_change":35.106212909911,"total_market_cap_yesterday":3863946308480.901,"total_volume_24h_yesterday":169381476135.08,"total_market_cap_yesterday_percentage_change":-2.803138964863308,"total_volume_24h_yesterday_percentage_change":21.21641085775569,"last_updated":"2025-08-01T16:03:59.999Z"}},"last_updated":"2025-08-01T16:03:59.999Z"}}
{"status":{"timestamp":"2025-08-01T17:06:47.589Z","error_code":0,"error_message":null,"elapsed":32,"credit_count":1,"notice":null},"data":{"active_cryptocurrencies":9489,"total_cryptocurrencies":35496,"active_market_pairs":106786,"active_exchanges":834,"total_exchanges":10795,"eth_dominance":11.557515818378,"btc_dominance":61.23856687004,"eth_dominance_yesterday":11.81865205,"btc_dominance_yesterday":60.84021011,"eth_dominance_24h_percentage_change":-0.261136231622,"btc_dominance_24h_percentage_change":0.39835676004,"defi_volume_24h":43285104816.66301,"defi_volume_24h_reported":96793721282.7832,"defi_market_cap":100809306432.76271,"defi_24h_percentage_change":2.505557573771,"stablecoin_volume_24h":196234387497.75647,"stablecoin_volume_24h_reported":1083218568528.7172,"stablecoin_market_cap":248571031889.8322,"stablecoin_24h_percentage_change":18.384628169504,"derivatives_volume_24h":2040281514106.7869,"derivatives_volume_24h_reported":2040281514106.7869,"derivatives_24h_percentage_change":33.376255183742,"total_crypto_dex_currencies":18968234,"today_incremental_crypto_number":5,"past_24h_incremental_crypto_number":23225,"past_7d_incremental_crypto_number":155912,"past_30d_incremental_crypto_number":921571,"today_change_percent":0.01131493221,"tracked_yearly_number":{"maxIncrementalNumber":184087,"minIncrementalNumber":2147,"maxIncrementalDate":"2025-04-17T00:00:00.000Z","minIncrementalDate":"2025-08-01T00:00:00.000Z"},"quote":{"USD":{"total_market_cap":3728350742380.0405,"total_volume_24h":202666273479.9,"total_volume_24h_reported":1106856595185.44,"altcoin_volume_24h":114038197540.41125,"altcoin_volume_24h_reported":751957947263.5857,"altcoin_market_cap":1445162179858.012,"defi_volume_24h":43285104816.66301,"defi_volume_24h_reported":96793721282.7832,"defi_24h_percentage_change":2.505557573771,"defi_market_cap":100809306432.76271,"stablecoin_volume_24h":196234387497.75647,"stablecoin_volume_24h_reported":1083218568528.7172,"stablecoin_24h_percentage_change":18.384628169504,"stablecoin_market_cap":248571031889.8322,"derivatives_volume_24h":2040281514106.7869,"derivatives_volume_24h_reported":2040281514106.7869,"derivatives_24h_percentage_change":33.376255183742,"total_market_cap_yesterday":3868048221731.9404,"total_volume_24h_yesterday":169875394069.89,"total_market_cap_yesterday_percentage_change":-3.6115754340143553,"total_volume_24h_yesterday_percentage_change":19.302901158551066,"last_updated":"2025-08-01T17:03:59.999Z"}},"last_updated":"2025-08-01T17:03:59.999Z"}}
{"status":{"timestamp":"2025-08-01T18:06:42.580Z","error_code":0,"error_message":null,"elapsed":51,"credit_count":1,"notice":null},"data":{"active_cryptocurrencies":9489,"total_cryptocurrencies":35496,"active_market_pairs":106789,"active_exchanges":834,"total_exchanges":10795,"eth_dominance":11.541101134852,"btc_dominance":61.191053643008,"eth_dominance_yesterday":11.83029006,"btc_dominance_yesterday":60.86567318,"eth_dominance_24h_percentage_change":-0.289188925148,"btc_dominance_24h_percentage_change":0.325380463008,"defi_volume_24h":43029940971.36645,"defi_volume_24h_reported":96791398498.3525,"defi_market_cap":100465624762.89456,"defi_24h_percentage_change":2.241380204949,"stablecoin_volume_24h":198062069186.22122,"stablecoin_volume_24h_reported":1089201376883.672,"stablecoin_market_cap":248701192695.89807,"stablecoin_24h_percentage_change":19.335386858556,"derivatives_volume_24h":2050764147598.726,"derivatives_volume_24h_reported":2050764147598.726,"derivatives_24h_percentage_change":32.46324829234,"total_crypto_dex_currencies":18968234,"today_incremental_crypto_number":5,"past_24h_incremental_crypto_number":23225,"past_7d_incremental_crypto_number":155912,"past_30d_incremental_crypto_number":921571,"today_change_percent":0.01131493221,"tracked_yearly_number":{"maxIncrementalNumber":184087,"minIncrementalNumber":2147,"maxIncrementalDate":"2025-04-17T00:00:00.000Z","minIncrementalDate":"2025-08-01T00:00:00.000Z"},"quote":{"USD":{"total_market_cap":3714498237549.184,"total_volume_24h":205671512772.4,"total_volume_24h_reported":1115074265748.47,"altcoin_volume_24h":115344085281.18854,"altcoin_volume_24h_reported":756396633837.4718,"altcoin_market_cap":1441557628441.861,"defi_volume_24h":43029940971.36645,"defi_volume_24h_reported":96791398498.3525,"defi_24h_percentage_change":2.241380204949,"defi_market_cap":100465624762.89456,"stablecoin_volume_24h":198062069186.22122,"stablecoin_volume_24h_reported":1089201376883.672,"stablecoin_24h_percentage_change":19.335386858556,"stablecoin_market_cap":248701192695.89807,"derivatives_volume_24h":2050764147598.726,"derivatives_volume_24h_reported":2050764147598.726,"derivatives_24h_percentage_change":32.46324829234,"total_market_cap_yesterday":3847115977651.2764,"total_volume_24h_yesterday":170741331852.9,"total_market_cap_yesterday_percentage_change":-3.447198911405252,"total_volume_24h_yesterday_percentage_change":20.457952705671545,"last_updated":"2025-08-01T18:04:59.999Z"}},"last_updated":"2025-08-01T18:04:59.999Z"}}
{"status":{"timestamp":"2025-08-01T19:05:50.274Z","error_code":0,"error_message":null,"elapsed":124,"credit_count":1,"notice":null},"data":{"active_cryptocurrencies":9487,"total_cryptocurrencies":35496,"active_market_pairs":106793,"active_exchanges":834,"total_exchanges":10795,"eth_dominance":11.550226205174,"btc_dominance":61.072256218838,"eth_dominance_yesterday":11.84310751,"btc_dominance_yesterday":60.851997,"eth_dominance_24h_percentage_change":-0.292881304826,"btc_dominance_24h_percentage_change":0.220259218838,"defi_volume_24h":42922120576.45678,"defi_volume_24h_reported":97241200977.51526,"defi_market_cap":100620773923.90918,"defi_24h_percentage_change":3.158030863486,"stablecoin_volume_24h":200364840410.71536,"stablecoin_volume_24h_reported":1104769424934.7593,"stablecoin_market_cap":248805311033.61066,"stablecoin_24h_percentage_change":23.693004043249,"derivatives_volume_24h":2087178712897.0627,"derivatives_volume_24h_reported":2087178712897.0627,"derivatives_24h_percentage_change":39.128537998057,"total_crypto_dex_currencies":18968234,"today_incremental_crypto_number":5,"past_24h_incremental_crypto_number":23225,"past_7d_incremental_crypto_number":155912,"past_30d_incremental_crypto_number":921571,"today_change_percent":0.01131493221,"tracked_yearly_number":{"maxIncrementalNumber":184087,"minIncrementalNumber":2147,"maxIncrementalDate":"2025-04-17T00:00:00.000Z","minIncrementalDate":"2025-08-01T00:00:00.000Z"},"quote":{"USD":{"total_market_cap":3705996051847.4585,"total_volume_24h":207481445876.43,"total_volume_24h_reported":1130513276297.44,"altcoin_volume_24h":116753069255.25255,"altcoin_volume_24h_reported":765599083487.8401,"altcoin_market_cap":1442660647603.1462,"defi_volume_24h":42922120576.45678,"defi_volume_24h_reported":97241200977.51526,"defi_24h_percentage_change":3.158030863486,"defi_market_cap":100620773923.90918,"stablecoin_volume_24h":200364840410.71536,"stablecoin_volume_24h_reported":1104769424934.7593,"stablecoin_24h_percentage_change":23.693004043249,"stablecoin_market_cap":248805311033.61066,"derivatives_volume_24h":2087178712897.0627,"derivatives_volume_24h_reported":2087178712897.0627,"derivatives_24h_percentage_change":39.128537998057,"total_market_cap_yesterday":3847215540658.4165,"total_volume_24h_yesterday":165927681863.83,"total_market_cap_yesterday_percentage_change":-3.6706934487686596,"total_volume_24h_yesterday_percentage_change":25.043298107847647,"last_updated":"2025-08-01T19:03:59.999Z"}},"last_updated":"2025-08-01T19:03:59.999Z"}}
{"status":{"timestamp":"2025-08-01T20:05:21.500Z","error_code":0,"error_message":null,"elapsed":26,"credit_count":1,"notice":null},"data":{"active_cryptocurrencies":9485,"total_cryptocurrencies":35496,"active_market_pairs":106780,"active_exchanges":834,"total_exchanges":10796,"eth_dominance":11.499606257925,"btc_dominance":61.001815997232,"eth_dominance_yesterday":11.81920157,"btc_dominance_yesterday":60.87473862,"eth_dominance_24h_percentage_change":-0.319595312075,"btc_dominance_24h_percentage_change":0.127077377232,"defi_volume_24h":42973153043.8292,"defi_volume_24h_reported":97459584416.95766,"defi_market_cap":101144442202.40501,"defi_24h_percentage_change":6.527825510154,"stablecoin_volume_24h":201786957453.518,"stablecoin_volume_24h_reported":1112091110690.5002,"stablecoin_market_cap":248696800088.22983,"stablecoin_24h_percentage_change":31.207997246306,"derivatives_volume_24h":2106495302554.9539,"derivatives_volume_24h_reported":2106495302554.9539,"derivatives_24h_percentage_change":50.053941470126,"total_crypto_dex_currencies":18968234,"today_incremental_crypto_number":5,"past_24h_incremental_crypto_number":23225,"past_7d_incremental_crypto_number":155912,"past_30d_incremental_crypto_number":921571,"today_change_percent":0.01131493221,"tracked_yearly_number":{"maxIncrementalNumber":184087,"minIncrementalNumber":2147,"maxIncrementalDate":"2025-04-17T00:00:00.000Z","minIncrementalDate":"2025-08-01T00:00:00.000Z"},"quote":{"USD":{"total_market_cap":3700983182684.749,"total_volume_24h":209497367036.87,"total_volume_24h_reported":1137057963971.49,"altcoin_volume_24h":117709882871.58801,"altcoin_volume_24h_reported":770847774820.0839,"altcoin_market_cap":1443316231494.881,"defi_volume_24h":42973153043.8292,"defi_volume_24h_reported":97459584416.95766,"defi_24h_percentage_change":6.527825510154,"defi_market_cap":101144442202.40501,"stablecoin_volume_24h":201786957453.518,"stablecoin_volume_24h_reported":1112091110690.5002,"stablecoin_24h_percentage_change":31.207997246306,"stablecoin_market_cap":248696800088.22983,"derivatives_volume_24h":2106495302554.9539,"derivatives_volume_24h_reported":2106495302554.9539,"derivatives_24h_percentage_change":50.053941470126,"total_market_cap_yesterday":3819895175202.0493,"total_volume_24h_yesterday":157447496883.02,"total_market_cap_yesterday_percentage_change":-3.1129648082819585,"total_volume_24h_yesterday_percentage_change":33.058556778785714,"last_updated":"2025-08-01T20:02:59.999Z"}},"last_updated":"2025-08-01T20:02:59.999Z"}}
{"status":{"timestamp":"2025-08-01T21:04:56.684Z","error_code":0,"error_message":null,"elapsed":25,"credit_count":1,"notice":null},"data":{"active_cryptocurrencies":9485,"total_cryptocurrencies":35496,"active_market_pairs":106773,"active_exchanges":834,"total_exchanges":10796,"eth_dominance":11.530720540866,"btc_dominance":61.138982609084,"eth_dominance_yesterday":11.83782694,"btc_dominance_yesterday":60.83858827,"eth_dominance_24h_percentage_change":-0.307106399134,"btc_dominance_24h_percentage_change":0.300394339084,"defi_volume_24h":43238695234.952194,"defi_volume_24h_reported":98193502422.04204,"defi_market_cap":100673320744.98871,"defi_24h_percentage_change":7.144735338307,"stablecoin_volume_24h":202564748734.81146,"stablecoin_volume_24h_reported":1119097856790.4277,"stablecoin_market_cap":248918767937.02792,"stablecoin_24h_percentage_change":31.533577389245,"derivatives_volume_24h":2122476741826.9292,"derivatives_volume_24h_reported":2122476741826.9292,"derivatives_24h_percentage_change":49.604861046066,"total_crypto_dex_currencies":18968234,"today_incremental_crypto_number":5,"past_24h_incremental_crypto_number":23225,"past_7d_incremental_crypto_number":155912,"past_30d_incremental_crypto_number":921571,"today_change_percent":0.01131493221,"tracked_yearly_number":{"maxIncrementalNumber":184087,"minIncrementalNumber":2147,"maxIncrementalDate":"2025-04-17T00:00:00.000Z","minIncrementalDate":"2025-08-01T00:00:00.000Z"},"quote":{"USD":{"total_market_cap":3708678052396.163,"total_volume_24h":209645379141.04,"total_volume_24h_reported":1146567608027.68,"altcoin_volume_24h":118622427478.99945,"altcoin_volume_24h_reported":779542757612.3467,"altcoin_market_cap":1441230022914.7727,"defi_volume_24h":43238695234.952194,"defi_volume_24h_reported":98193502422.04204,"defi_24h_percentage_change":7.144735338307,"defi_market_cap":100673320744.98871,"stablecoin_volume_24h":202564748734.81146,"stablecoin_volume_24h_reported":1119097856790.4277,"stablecoin_24h_percentage_change":31.533577389245,"stablecoin_market_cap":248918767937.02792,"derivatives_volume_24h":2122476741826.9292,"derivatives_volume_24h_reported":2122476741826.9292,"derivatives_24h_percentage_change":49.604861046066,"total_market_cap_yesterday":3810707127681.0645,"total_volume_24h_yesterday":157417906368.86,"total_market_cap_yesterday_percentage_change":-2.6774315597165526,"total_volume_24h_yesterday_percentage_change":33.17759331000195,"last_updated":"2025-08-01T21:02:59.999Z"}},"last_updated":"2025-08-01T21:02:59.999Z"}}
