{"status":{"timestamp":"2026-03-01T00:29:10.257Z","error_code":0,"error_message":null,"elapsed":13,"credit_count":1,"notice":null},"data":{"active_cryptocurrencies":8737,"total_cryptocurrencies":37172,"active_market_pairs":116682,"active_exchanges":924,"total_exchanges":11862,"eth_dominance":10.284271526216,"btc_dominance":58.113542186845,"eth_dominance_yesterday":10.24397621,"btc_dominance_yesterday":57.95786821,"eth_dominance_24h_percentage_change":0.040295316216,"btc_dominance_24h_percentage_change":0.155673976845,"defi_volume_24h":10578079357.204855,"defi_volume_24h_reported":36710856129.74433,"defi_market_cap":57788167539.54973,"defi_24h_percentage_change":13.101498071865,"stablecoin_volume_24h":99089962218.59187,"stablecoin_volume_24h_reported":586759623233.8922,"stablecoin_market_cap":285848865199.3932,"stablecoin_24h_percentage_change":3.84766237763,"derivatives_volume_24h":951694020050.3561,"derivatives_volume_24h_reported":987478177996.0782,"derivatives_24h_percentage_change":15.124852695213,"total_crypto_dex_currencies":36091878,"today_incremental_crypto_number":0,"past_24h_incremental_crypto_number":159028,"past_7d_incremental_crypto_number":851090,"past_30d_incremental_crypto_number":4693020,"today_change_percent":0.000041560614,"tracked_yearly_number":{"maxIncrementalNumber":1305553,"minIncrementalNumber":16,"maxIncrementalDate":"2025-07-08T00:00:00.000Z","minIncrementalDate":"2026-02-28T00:00:00.000Z"},"quote":{"USD":{"total_market_cap":2301111068268.334,"total_volume_24h":102156613636.61,"total_volume_24h_reported":598479337703.82,"altcoin_volume_24h":60240535661.93448,"altcoin_volume_24h_reported":362649862867.214,"altcoin_market_cap":963853916844.065,"defi_volume_24h":10578079357.204855,"defi_volume_24h_reported":36710856129.74433,"defi_24h_percentage_change":13.101498071865,"defi_market_cap":57788167539.54973,"stablecoin_volume_24h":99089962218.59187,"stablecoin_volume_24h_reported":586759623233.8922,"stablecoin_24h_percentage_change":3.84766237763,"stablecoin_market_cap":285848865199.3932,"derivatives_volume_24h":951694020050.3561,"derivatives_volume_24h_reported":987478177996.0782,"derivatives_24h_percentage_change":15.124852695213,"total_market_cap_yesterday":2270379101991.8423,"total_volume_24h_yesterday":96421249681.57,"total_market_cap_yesterday_percentage_change":1.3536050543070104,"total_volume_24h_yesterday_percentage_change":5.948236487269099,"last_updated":"2026-03-01T00:26:59.999Z"}},"last_updated":"2026-03-01T00:26:59.999Z"}}
{"status":{"timestamp":"2026-03-01T01:34:55.889Z","error_code":0,"error_message":null,"elapsed":15,"credit_count":1,"notice":null},"data":{"active_cryptocurrencies":8736,"total_cryptocurrencies":37172,"active_market_pairs":116685,"active_exchanges":924,"total_exchanges":11862,"eth_dominance":10.306567058765,"btc_dominance":57.983346874903,"eth_dominance_yesterday":10.22632455,"btc_dominance_yesterday":57.96163782,"eth_dominance_24h_percentage_change":0.080242508765,"btc_dominance_24h_percentage_change":0.021709054903,"defi_volume_24h":10782535749.416777,"defi_volume_24h_reported":37230636109.18114,"defi_market_cap":57288043182.53715,"defi_24h_percentage_change":16.152913393077,"stablecoin_volume_24h":100670927981.95088,"stablecoin_volume_24h_reported":596389215747.3615,"stablecoin_market_cap":285885343508.27594,"stablecoin_24h_percentage_change":5.621050073077,"derivatives_volume_24h":962341926687.8694,"derivatives_volume_24h_reported":997352655318.944,"derivatives_24h_percentage_change":17.800119909778,"total_crypto_dex_currencies":36091878,"today_incremental_crypto_number":0,"past_24h_incremental_crypto_number":159028,"past_7d_incremental_crypto_number":851090,"past_30d_incremental_crypto_number":4693020,"today_change_percent":0.000041560614,"tracked_yearly_number":{"maxIncrementalNumber":1305553,"minIncrementalNumber":16,"maxIncrementalDate":"2025-07-08T00:00:00.000Z","minIncrementalDate":"2026-02-28T00:00:00.000Z"},"quote":{"USD":{"total_market_cap":2289100429112.7007,"total_volume_24h":103702289685.07,"total_volume_24h_reported":608223783400.01,"altcoin_volume_24h":60963472465.418564,"altcoin_volume_24h_reported":366566157915.89484,"altcoin_market_cap":961803386985.3932,"defi_volume_24h":10782535749.416777,"defi_volume_24h_reported":37230636109.18114,"defi_24h_percentage_change":16.152913393077,"defi_market_cap":57288043182.53715,"stablecoin_volume_24h":100670927981.95088,"stablecoin_volume_24h_reported":596389215747.3615,"stablecoin_24h_percentage_change":5.621050073077,"stablecoin_market_cap":285885343508.27594,"derivatives_volume_24h":962341926687.8694,"derivatives_volume_24h_reported":997352655318.944,"derivatives_24h_percentage_change":17.800119909778,"total_market_cap_yesterday":2269363319291.497,"total_volume_24h_yesterday":96151608902.29,"total_market_cap_yesterday_percentage_change":0.8697201392752589,"total_volume_24h_yesterday_percentage_change":7.852890730568092,"last_updated":"2026-03-01T01:32:59.999Z"}},"last_updated":"2026-03-01T01:32:59.999Z"}}
{"status":{"timestamp":"2026-03-01T03:05:07.357Z","error_code":0,"error_message":null,"elapsed":16,"credit_count":1,"notice":null},"data":{"active_cryptocurrencies":8737,"total_cryptocurrencies":37172,"active_market_pairs":116687,"active_exchanges":924,"total_exchanges":11862,"eth_dominance":10.516168474435,"btc_dominance":57.90453736977,"eth_dominance_yesterday":10.23965877,"btc_dominance_yesterday":57.96490665,"eth_dominance_24h_percentage_change":0.276509704435,"btc_dominance_24h_percentage_change":-0.06036928023,"defi_volume_24h":11759900272.856384,"defi_volume_24h_reported":39435904332.96088,"defi_market_cap":58805255731.847946,"defi_24h_percentage_change":29.364171291338,"stablecoin_volume_24h":110764146216.66075,"stablecoin_volume_24h_reported":657563872373.6873,"stablecoin_market_cap":285835836963.7292,"stablecoin_24h_percentage_change":19.583316326517,"derivatives_volume_24h":1063378876842.4501,"derivatives_volume_24h_reported":1101619741823.744,"derivatives_24h_percentage_change":33.457683025959,"total_crypto_dex_currencies":36246697,"today_incremental_crypto_number":0,"past_24h_incremental_crypto_number":154811,"past_7d_incremental_crypto_number":870640,"past_30d_incremental_crypto_number":4646824,"today_change_percent":0.000068971849,"tracked_yearly_number":{"maxIncrementalNumber":1305553,"minIncrementalNumber":26,"maxIncrementalDate":"2025-07-08T00:00:00.000Z","minIncrementalDate":"2026-03-01T00:00:00.000Z"},"quote":{"USD":{"total_market_cap":2336964707592.7446,"total_volume_24h":114229098928.26,"total_volume_24h_reported":670662232974.81,"altcoin_volume_24h":67274913853.89438,"altcoin_volume_24h_reported":403291563282.5887,"altcoin_market_cap":983756105166.3765,"defi_volume_24h":11759900272.856384,"defi_volume_24h_reported":39435904332.96088,"defi_24h_percentage_change":29.364171291338,"defi_market_cap":58805255731.847946,"stablecoin_volume_24h":110764146216.66075,"stablecoin_volume_24h_reported":657563872373.6873,"stablecoin_24h_percentage_change":19.583316326517,"stablecoin_market_cap":285835836963.7292,"derivatives_volume_24h":1063378876842.4501,"derivatives_volume_24h_reported":1101619741823.744,"derivatives_24h_percentage_change":33.457683025959,"total_market_cap_yesterday":2272643491853.8105,"total_volume_24h_yesterday":93550037967.94,"total_market_cap_yesterday_percentage_change":2.8302378252238185,"total_volume_24h_yesterday_percentage_change":22.104813006496897,"last_updated":"2026-03-01T03:03:59.999Z"}},"last_updated":"2026-03-01T03:03:59.999Z"}}
